{
  "Bicycle.swift" : {
    "key.substructure" : [
      {
        "key.kind" : "source.lang.swift.decl.class",
        "key.offset" : 94,
        "key.parsed_declaration" : "public class Bicycle",
        "key.doc.comment" : "🚲 A two-wheeled, human-powered mode of transportation.",
        "key.namelength" : 7,
        "key.doc.line" : 4,
        "key.bodylength" : 2193,
        "key.length" : 7,
        "key.doc.column" : 14,
        "key.parsed_scope.end" : 89,
        "key.usr" : "s:C7Bicycle7Bicycle",
        "key.doc.file" : "Bicycle.swift",
        "key.nameoffset" : 94,
        "key.annotated_decl" : "<Declaration>public class Bicycle<\/Declaration>",
        "key.accessibility" : "source.lang.swift.accessibility.public",
        "key.runtime_name" : "_TtC8__main__7Bicycle",
        "key.parsed_scope.start" : 4,
        "key.filepath" : "Bicycle.swift",
        "key.bodyoffset" : 103,
        "key.doc.declaration" : "public class Bicycle",
        "key.name" : "Bicycle",
        "key.typename" : "Bicycle.Type",
        "key.doc.type" : "Class",
        "key.attributes" : [
          {
            "key.attribute" : "source.decl.attribute.__raw_doc_comment"
          }
        ],
        "key.doc.full_as_xml" : "<Class file=\"Bicycle.swift\" line=\"4\" column=\"14\"><Name>Bicycle<\/Name><USR>s:C7Bicycle7Bicycle<\/USR><Declaration>public class Bicycle<\/Declaration><Abstract><Para>🚲 A two-wheeled, human-powered mode of transportation.<\/Para><\/Abstract><\/Class>",
        "key.doc.name" : "Bicycle",
        "key.substructure" : [
          {
            "key.kind" : "source.lang.swift.decl.enum",
            "key.offset" : 334,
            "key.parsed_declaration" : "public enum Style",
            "key.doc.comment" : "Frame and construction style.\n\n- Road: For streets or trails.\n- Touring: For long journeys.\n- Cruiser: For casual trips around town.\n- Hybrid: For general-purpose transportation.",
            "key.namelength" : 5,
            "key.doc.line" : 13,
            "key.bodylength" : 49,
            "key.length" : 5,
            "key.doc.column" : 17,
            "key.parsed_scope.end" : 15,
            "key.usr" : "s:OC7Bicycle7Bicycle5Style",
            "key.doc.file" : "Bicycle.swift",
            "key.nameoffset" : 334,
            "key.annotated_decl" : "<Declaration>public enum Style<\/Declaration>",
            "key.accessibility" : "source.lang.swift.accessibility.public",
            "key.parsed_scope.start" : 13,
            "key.filepath" : "Bicycle.swift",
            "key.bodyoffset" : 341,
            "key.doc.declaration" : "public enum Style",
            "key.name" : "Style",
            "key.typename" : "Bicycle.Style.Type",
            "key.doc.type" : "Other",
            "key.attributes" : [
              {
                "key.attribute" : "source.decl.attribute.__raw_doc_comment"
              }
            ],
            "key.doc.full_as_xml" : "<Other file=\"Bicycle.swift\" line=\"13\" column=\"17\"><Name>Style<\/Name><USR>s:OC7Bicycle7Bicycle5Style<\/USR><Declaration>public enum Style<\/Declaration><Abstract><Para>Frame and construction style.<\/Para><\/Abstract><Discussion><List-Bullet><Item><Para>Road: For streets or trails.<\/Para><\/Item><Item><Para>Touring: For long journeys.<\/Para><\/Item><Item><Para>Cruiser: For casual trips around town.<\/Para><\/Item><Item><Para>Hybrid: For general-purpose transportation.<\/Para><\/Item><\/List-Bullet><\/Discussion><\/Other>",
            "key.doc.name" : "Style",
            "key.substructure" : [
              {
                "key.substructure" : [
                  {
                    "key.kind" : "source.lang.swift.decl.enumelement",
                    "key.offset" : 355,
                    "key.parsed_declaration" : "case Road, Touring, Cruiser, Hybrid",
                    "key.namelength" : 4,
                    "key.length" : 4,
                    "key.name" : "Road",
                    "key.typename" : "Bicycle.Style.Type -> Bicycle.Style",
                    "key.parsed_scope.end" : 14,
                    "key.usr" : "s:FOC7Bicycle7Bicycle5Style4RoadFMS1_S1_",
                    "key.nameoffset" : 355,
                    "key.annotated_decl" : "<Declaration><\/Declaration>",
                    "key.accessibility" : "source.lang.swift.accessibility.internal",
                    "key.parsed_scope.start" : 14,
                    "key.filepath" : "Bicycle.swift"
                  },
                  {
                    "key.kind" : "source.lang.swift.decl.enumelement",
                    "key.offset" : 361,
                    "key.parsed_declaration" : "case Road, Touring, Cruiser, Hybrid",
                    "key.namelength" : 7,
                    "key.length" : 7,
                    "key.name" : "Touring",
                    "key.typename" : "Bicycle.Style.Type -> Bicycle.Style",
                    "key.parsed_scope.end" : 14,
                    "key.usr" : "s:FOC7Bicycle7Bicycle5Style7TouringFMS1_S1_",
                    "key.nameoffset" : 361,
                    "key.annotated_decl" : "<Declaration><\/Declaration>",
                    "key.accessibility" : "source.lang.swift.accessibility.internal",
                    "key.parsed_scope.start" : 14,
                    "key.filepath" : "Bicycle.swift"
                  },
                  {
                    "key.kind" : "source.lang.swift.decl.enumelement",
                    "key.offset" : 370,
                    "key.parsed_declaration" : "case Road, Touring, Cruiser, Hybrid",
                    "key.namelength" : 7,
                    "key.length" : 7,
                    "key.name" : "Cruiser",
                    "key.typename" : "Bicycle.Style.Type -> Bicycle.Style",
                    "key.parsed_scope.end" : 14,
                    "key.usr" : "s:FOC7Bicycle7Bicycle5Style7CruiserFMS1_S1_",
                    "key.nameoffset" : 370,
                    "key.annotated_decl" : "<Declaration><\/Declaration>",
                    "key.accessibility" : "source.lang.swift.accessibility.internal",
                    "key.parsed_scope.start" : 14,
                    "key.filepath" : "Bicycle.swift"
                  },
                  {
                    "key.kind" : "source.lang.swift.decl.enumelement",
                    "key.offset" : 379,
                    "key.parsed_declaration" : "case Road, Touring, Cruiser, Hybrid",
                    "key.namelength" : 6,
                    "key.length" : 6,
                    "key.name" : "Hybrid",
                    "key.typename" : "Bicycle.Style.Type -> Bicycle.Style",
                    "key.parsed_scope.end" : 14,
                    "key.usr" : "s:FOC7Bicycle7Bicycle5Style6HybridFMS1_S1_",
                    "key.nameoffset" : 379,
                    "key.annotated_decl" : "<Declaration><\/Declaration>",
                    "key.accessibility" : "source.lang.swift.accessibility.internal",
                    "key.parsed_scope.start" : 14,
                    "key.filepath" : "Bicycle.swift"
                  }
                ],
                "key.kind" : "source.lang.swift.decl.enumcase",
                "key.offset" : 350,
                "key.nameoffset" : 0,
                "key.namelength" : 0,
                "key.length" : 35
              }
            ],
            "key.doc.discussion" : [
              {
                "List-Bullet" : ""
              }
            ]
          },
          {
            "key.kind" : "source.lang.swift.decl.enum",
            "key.offset" : 569,
            "key.parsed_declaration" : "public enum Gearing",
            "key.doc.comment" : "Mechanism for converting pedal power into motion.\n\n- Fixed: A single, fixed gear.\n- Freewheel: A variable-speed, disengageable gear.",
            "key.namelength" : 7,
            "key.doc.line" : 23,
            "key.bodylength" : 60,
            "key.length" : 7,
            "key.doc.column" : 17,
            "key.parsed_scope.end" : 26,
            "key.usr" : "s:OC7Bicycle7Bicycle7Gearing",
            "key.doc.file" : "Bicycle.swift",
            "key.nameoffset" : 569,
            "key.annotated_decl" : "<Declaration>public enum Gearing<\/Declaration>",
            "key.accessibility" : "source.lang.swift.accessibility.public",
            "key.parsed_scope.start" : 23,
            "key.filepath" : "Bicycle.swift",
            "key.bodyoffset" : 578,
            "key.doc.declaration" : "public enum Gearing",
            "key.name" : "Gearing",
            "key.typename" : "Bicycle.Gearing.Type",
            "key.doc.type" : "Other",
            "key.attributes" : [
              {
                "key.attribute" : "source.decl.attribute.__raw_doc_comment"
              }
            ],
            "key.doc.full_as_xml" : "<Other file=\"Bicycle.swift\" line=\"23\" column=\"17\"><Name>Gearing<\/Name><USR>s:OC7Bicycle7Bicycle7Gearing<\/USR><Declaration>public enum Gearing<\/Declaration><Abstract><Para>Mechanism for converting pedal power into motion.<\/Para><\/Abstract><Discussion><List-Bullet><Item><Para>Fixed: A single, fixed gear.<\/Para><\/Item><Item><Para>Freewheel: A variable-speed, disengageable gear.<\/Para><\/Item><\/List-Bullet><\/Discussion><\/Other>",
            "key.doc.name" : "Gearing",
            "key.substructure" : [
              {
                "key.substructure" : [
                  {
                    "key.kind" : "source.lang.swift.decl.enumelement",
                    "key.offset" : 592,
                    "key.parsed_declaration" : "case Fixed",
                    "key.namelength" : 5,
                    "key.length" : 5,
                    "key.name" : "Fixed",
                    "key.typename" : "Bicycle.Gearing.Type -> Bicycle.Gearing",
                    "key.parsed_scope.end" : 24,
                    "key.usr" : "s:FOC7Bicycle7Bicycle7Gearing5FixedFMS1_S1_",
                    "key.nameoffset" : 592,
                    "key.annotated_decl" : "<Declaration><\/Declaration>",
                    "key.accessibility" : "source.lang.swift.accessibility.internal",
                    "key.parsed_scope.start" : 24,
                    "key.filepath" : "Bicycle.swift"
                  }
                ],
                "key.kind" : "source.lang.swift.decl.enumcase",
                "key.offset" : 587,
                "key.nameoffset" : 0,
                "key.namelength" : 0,
                "key.length" : 10
              },
              {
                "key.substructure" : [
                  {
                    "key.kind" : "source.lang.swift.decl.enumelement",
                    "key.offset" : 611,
                    "key.parsed_declaration" : "case Freewheel(speeds: Int)",
                    "key.namelength" : 9,
                    "key.length" : 9,
                    "key.name" : "Freewheel",
                    "key.typename" : "Bicycle.Gearing.Type -> (speeds: Int) -> Bicycle.Gearing",
                    "key.parsed_scope.end" : 25,
                    "key.usr" : "s:FOC7Bicycle7Bicycle7Gearing9FreewheelFMS1_FT6speedsSi_S1_",
                    "key.nameoffset" : 611,
                    "key.annotated_decl" : "<Declaration><\/Declaration>",
                    "key.accessibility" : "source.lang.swift.accessibility.internal",
                    "key.parsed_scope.start" : 25,
                    "key.filepath" : "Bicycle.swift"
                  }
                ],
                "key.kind" : "source.lang.swift.decl.enumcase",
                "key.offset" : 606,
                "key.nameoffset" : 0,
                "key.namelength" : 0,
                "key.length" : 27
              }
            ],
            "key.doc.discussion" : [
              {
                "List-Bullet" : ""
              }
            ]
          },
          {
            "key.kind" : "source.lang.swift.decl.enum",
            "key.offset" : 837,
            "key.parsed_declaration" : "enum Handlebar",
            "key.doc.comment" : "Hardware used for steering.\n\n- Riser: A casual handlebar.\n- Café: An upright handlebar.\n- Drop: A classic handlebar.\n- Bullhorn: A powerful handlebar.",
            "key.namelength" : 9,
            "key.doc.line" : 36,
            "key.bodylength" : 47,
            "key.length" : 9,
            "key.doc.column" : 10,
            "key.parsed_scope.end" : 38,
            "key.usr" : "s:OC7Bicycle7Bicycle9Handlebar",
            "key.doc.file" : "Bicycle.swift",
            "key.nameoffset" : 837,
            "key.annotated_decl" : "<Declaration>enum Handlebar<\/Declaration>",
            "key.accessibility" : "source.lang.swift.accessibility.internal",
            "key.parsed_scope.start" : 36,
            "key.filepath" : "Bicycle.swift",
            "key.bodyoffset" : 848,
            "key.doc.declaration" : "enum Handlebar",
            "key.name" : "Handlebar",
            "key.typename" : "Bicycle.Handlebar.Type",
            "key.doc.type" : "Other",
            "key.attributes" : [
              {
                "key.attribute" : "source.decl.attribute.__raw_doc_comment"
              }
            ],
            "key.doc.full_as_xml" : "<Other file=\"Bicycle.swift\" line=\"36\" column=\"10\"><Name>Handlebar<\/Name><USR>s:OC7Bicycle7Bicycle9Handlebar<\/USR><Declaration>enum Handlebar<\/Declaration><Abstract><Para>Hardware used for steering.<\/Para><\/Abstract><Discussion><List-Bullet><Item><Para>Riser: A casual handlebar.<\/Para><\/Item><Item><Para>Café: An upright handlebar.<\/Para><\/Item><Item><Para>Drop: A classic handlebar.<\/Para><\/Item><Item><Para>Bullhorn: A powerful handlebar.<\/Para><\/Item><\/List-Bullet><\/Discussion><\/Other>",
            "key.doc.name" : "Handlebar",
            "key.substructure" : [
              {
                "key.substructure" : [
                  {
                    "key.kind" : "source.lang.swift.decl.enumelement",
                    "key.offset" : 862,
                    "key.parsed_declaration" : "case Riser, Café, Drop, Bullhorn",
                    "key.namelength" : 5,
                    "key.length" : 5,
                    "key.name" : "Riser",
                    "key.typename" : "Bicycle.Handlebar.Type -> Bicycle.Handlebar",
                    "key.parsed_scope.end" : 37,
                    "key.usr" : "s:FOC7Bicycle7Bicycle9Handlebar5RiserFMS1_S1_",
                    "key.nameoffset" : 862,
                    "key.annotated_decl" : "<Declaration><\/Declaration>",
                    "key.accessibility" : "source.lang.swift.accessibility.internal",
                    "key.parsed_scope.start" : 37,
                    "key.filepath" : "Bicycle.swift"
                  },
                  {
                    "key.kind" : "source.lang.swift.decl.enumelement",
                    "key.offset" : 869,
                    "key.parsed_declaration" : "case Riser, Café, Drop, Bullhorn",
                    "key.namelength" : 5,
                    "key.length" : 5,
                    "key.name" : "Café",
                    "key.typename" : "Bicycle.Handlebar.Type -> Bicycle.Handlebar",
                    "key.parsed_scope.end" : 37,
                    "key.usr" : "s:FOC7Bicycle7Bicycle9HandlebarX7Caf_dmaFMS1_S1_",
                    "key.nameoffset" : 869,
                    "key.annotated_decl" : "<Declaration><\/Declaration>",
                    "key.accessibility" : "source.lang.swift.accessibility.internal",
                    "key.parsed_scope.start" : 37,
                    "key.filepath" : "Bicycle.swift"
                  },
                  {
                    "key.kind" : "source.lang.swift.decl.enumelement",
                    "key.offset" : 876,
                    "key.parsed_declaration" : "case Riser, Café, Drop, Bullhorn",
                    "key.namelength" : 4,
                    "key.length" : 4,
                    "key.name" : "Drop",
                    "key.typename" : "Bicycle.Handlebar.Type -> Bicycle.Handlebar",
                    "key.parsed_scope.end" : 37,
                    "key.usr" : "s:FOC7Bicycle7Bicycle9Handlebar4DropFMS1_S1_",
                    "key.nameoffset" : 876,
                    "key.annotated_decl" : "<Declaration><\/Declaration>",
                    "key.accessibility" : "source.lang.swift.accessibility.internal",
                    "key.parsed_scope.start" : 37,
                    "key.filepath" : "Bicycle.swift"
                  },
                  {
                    "key.kind" : "source.lang.swift.decl.enumelement",
                    "key.offset" : 882,
                    "key.parsed_declaration" : "case Riser, Café, Drop, Bullhorn",
                    "key.namelength" : 8,
                    "key.length" : 8,
                    "key.name" : "Bullhorn",
                    "key.typename" : "Bicycle.Handlebar.Type -> Bicycle.Handlebar",
                    "key.parsed_scope.end" : 37,
                    "key.usr" : "s:FOC7Bicycle7Bicycle9Handlebar8BullhornFMS1_S1_",
                    "key.nameoffset" : 882,
                    "key.annotated_decl" : "<Declaration><\/Declaration>",
                    "key.accessibility" : "source.lang.swift.accessibility.internal",
                    "key.parsed_scope.start" : 37,
                    "key.filepath" : "Bicycle.swift"
                  }
                ],
                "key.kind" : "source.lang.swift.decl.enumcase",
                "key.offset" : 857,
                "key.nameoffset" : 0,
                "key.namelength" : 0,
                "key.length" : 33
              }
            ],
            "key.doc.discussion" : [
              {
                "List-Bullet" : ""
              }
            ]
          },
          {
            "key.kind" : "source.lang.swift.decl.var.instance",
            "key.offset" : 940,
            "key.parsed_declaration" : "let style: Style",
            "key.doc.comment" : "The style of the bicycle.",
            "key.namelength" : 5,
            "key.doc.line" : 41,
            "key.length" : 5,
            "key.doc.declaration" : "let style: Bicycle.Bicycle.Style",
            "key.typename" : "Bicycle.Style",
            "key.name" : "style",
            "key.doc.column" : 9,
            "key.parsed_scope.end" : 41,
            "key.usr" : "s:vC7Bicycle7Bicycle5styleOS0_5Style",
            "key.doc.type" : "Other",
            "key.attributes" : [
              {
                "key.attribute" : "source.decl.attribute.__raw_doc_comment"
              }
            ],
            "key.doc.full_as_xml" : "<Other file=\"Bicycle.swift\" line=\"41\" column=\"9\"><Name>style<\/Name><USR>s:vC7Bicycle7Bicycle5styleOS0_5Style<\/USR><Declaration>let style: Bicycle.Bicycle.Style<\/Declaration><Abstract><Para>The style of the bicycle.<\/Para><\/Abstract><\/Other>",
            "key.nameoffset" : 940,
            "key.doc.file" : "Bicycle.swift",
            "key.annotated_decl" : "<Declaration>let style: <Type usr=\"s:C7Bicycle7Bicycle\">Bicycle<\/Type>.<Type usr=\"s:OC7Bicycle7Bicycle5Style\">Style<\/Type><\/Declaration>",
            "key.doc.name" : "style",
            "key.accessibility" : "source.lang.swift.accessibility.internal",
            "key.parsed_scope.start" : 41,
            "key.filepath" : "Bicycle.swift"
          },
          {
            "key.kind" : "source.lang.swift.decl.var.instance",
            "key.offset" : 998,
            "key.parsed_declaration" : "let gearing: Gearing",
            "key.doc.comment" : "The gearing of the bicycle.",
            "key.namelength" : 7,
            "key.doc.line" : 44,
            "key.length" : 7,
            "key.doc.declaration" : "let gearing: Bicycle.Bicycle.Gearing",
            "key.typename" : "Bicycle.Gearing",
            "key.name" : "gearing",
            "key.doc.column" : 9,
            "key.parsed_scope.end" : 44,
            "key.usr" : "s:vC7Bicycle7Bicycle7gearingOS0_7Gearing",
            "key.doc.type" : "Other",
            "key.attributes" : [
              {
                "key.attribute" : "source.decl.attribute.__raw_doc_comment"
              }
            ],
            "key.doc.full_as_xml" : "<Other file=\"Bicycle.swift\" line=\"44\" column=\"9\"><Name>gearing<\/Name><USR>s:vC7Bicycle7Bicycle7gearingOS0_7Gearing<\/USR><Declaration>let gearing: Bicycle.Bicycle.Gearing<\/Declaration><Abstract><Para>The gearing of the bicycle.<\/Para><\/Abstract><\/Other>",
            "key.nameoffset" : 998,
            "key.doc.file" : "Bicycle.swift",
            "key.annotated_decl" : "<Declaration>let gearing: <Type usr=\"s:C7Bicycle7Bicycle\">Bicycle<\/Type>.<Type usr=\"s:OC7Bicycle7Bicycle7Gearing\">Gearing<\/Type><\/Declaration>",
            "key.doc.name" : "gearing",
            "key.accessibility" : "source.lang.swift.accessibility.internal",
            "key.parsed_scope.start" : 44,
            "key.filepath" : "Bicycle.swift"
          },
          {
            "key.kind" : "source.lang.swift.decl.var.instance",
            "key.offset" : 1062,
            "key.parsed_declaration" : "let handlebar: Handlebar",
            "key.doc.comment" : "The handlebar of the bicycle.",
            "key.namelength" : 9,
            "key.doc.line" : 47,
            "key.length" : 9,
            "key.doc.declaration" : "let handlebar: Bicycle.Bicycle.Handlebar",
            "key.typename" : "Bicycle.Handlebar",
            "key.name" : "handlebar",
            "key.doc.column" : 9,
            "key.parsed_scope.end" : 47,
            "key.usr" : "s:vC7Bicycle7Bicycle9handlebarOS0_9Handlebar",
            "key.doc.type" : "Other",
            "key.attributes" : [
              {
                "key.attribute" : "source.decl.attribute.__raw_doc_comment"
              }
            ],
            "key.doc.full_as_xml" : "<Other file=\"Bicycle.swift\" line=\"47\" column=\"9\"><Name>handlebar<\/Name><USR>s:vC7Bicycle7Bicycle9handlebarOS0_9Handlebar<\/USR><Declaration>let handlebar: Bicycle.Bicycle.Handlebar<\/Declaration><Abstract><Para>The handlebar of the bicycle.<\/Para><\/Abstract><\/Other>",
            "key.nameoffset" : 1062,
            "key.doc.file" : "Bicycle.swift",
            "key.annotated_decl" : "<Declaration>let handlebar: <Type usr=\"s:C7Bicycle7Bicycle\">Bicycle<\/Type>.<Type usr=\"s:OC7Bicycle7Bicycle9Handlebar\">Handlebar<\/Type><\/Declaration>",
            "key.doc.name" : "handlebar",
            "key.accessibility" : "source.lang.swift.accessibility.internal",
            "key.parsed_scope.start" : 47,
            "key.filepath" : "Bicycle.swift"
          },
          {
            "key.kind" : "source.lang.swift.decl.var.instance",
            "key.offset" : 1139,
            "key.parsed_declaration" : "let frameSize: Int",
            "key.doc.comment" : "The size of the frame, in centimeters.",
            "key.namelength" : 9,
            "key.doc.line" : 50,
            "key.length" : 9,
            "key.doc.declaration" : "let frameSize: Int",
            "key.typename" : "Int",
            "key.name" : "frameSize",
            "key.doc.column" : 9,
            "key.parsed_scope.end" : 50,
            "key.usr" : "s:vC7Bicycle7Bicycle9frameSizeSi",
            "key.doc.type" : "Other",
            "key.attributes" : [
              {
                "key.attribute" : "source.decl.attribute.__raw_doc_comment"
              }
            ],
            "key.doc.full_as_xml" : "<Other file=\"Bicycle.swift\" line=\"50\" column=\"9\"><Name>frameSize<\/Name><USR>s:vC7Bicycle7Bicycle9frameSizeSi<\/USR><Declaration>let frameSize: Int<\/Declaration><Abstract><Para>The size of the frame, in centimeters.<\/Para><\/Abstract><\/Other>",
            "key.nameoffset" : 1139,
            "key.doc.file" : "Bicycle.swift",
            "key.annotated_decl" : "<Declaration>let frameSize: <Type usr=\"s:Si\">Int<\/Type><\/Declaration>",
            "key.doc.name" : "frameSize",
            "key.accessibility" : "source.lang.swift.accessibility.internal",
            "key.parsed_scope.start" : 50,
            "key.filepath" : "Bicycle.swift"
          },
          {
            "key.kind" : "source.lang.swift.decl.var.instance",
            "key.offset" : 1230,
            "key.parsed_declaration" : "private(set) var numberOfTrips: Int",
            "key.doc.comment" : "The number of trips travelled by the bicycle.",
            "key.namelength" : 13,
            "key.doc.line" : 53,
            "key.length" : 13,
            "key.doc.declaration" : "private(set) var numberOfTrips: Int",
            "key.typename" : "Int",
            "key.name" : "numberOfTrips",
            "key.doc.column" : 22,
            "key.parsed_scope.end" : 53,
            "key.usr" : "s:vC7Bicycle7Bicycle13numberOfTripsSi",
            "key.doc.type" : "Other",
            "key.attributes" : [
              {
                "key.attribute" : "source.decl.attribute.__raw_doc_comment"
              }
            ],
            "key.doc.full_as_xml" : "<Other file=\"Bicycle.swift\" line=\"53\" column=\"22\"><Name>numberOfTrips<\/Name><USR>s:vC7Bicycle7Bicycle13numberOfTripsSi<\/USR><Declaration>private(set) var numberOfTrips: Int<\/Declaration><Abstract><Para>The number of trips travelled by the bicycle.<\/Para><\/Abstract><\/Other>",
            "key.nameoffset" : 1230,
            "key.doc.file" : "Bicycle.swift",
            "key.annotated_decl" : "<Declaration>private(set) var numberOfTrips: <Type usr=\"s:Si\">Int<\/Type><\/Declaration>",
            "key.doc.name" : "numberOfTrips",
            "key.accessibility" : "source.lang.swift.accessibility.internal",
            "key.setter_accessibility" : "source.lang.swift.accessibility.private",
            "key.parsed_scope.start" : 53,
            "key.filepath" : "Bicycle.swift"
          },
          {
            "key.kind" : "source.lang.swift.decl.var.instance",
            "key.offset" : 1335,
            "key.parsed_declaration" : "private(set) var distanceTravelled: Double",
            "key.doc.comment" : "The total distance travelled by the bicycle, in meters.",
            "key.namelength" : 17,
            "key.doc.line" : 56,
            "key.length" : 17,
            "key.doc.declaration" : "private(set) var distanceTravelled: Double",
            "key.typename" : "Double",
            "key.name" : "distanceTravelled",
            "key.doc.column" : 22,
            "key.parsed_scope.end" : 56,
            "key.usr" : "s:vC7Bicycle7Bicycle17distanceTravelledSd",
            "key.doc.type" : "Other",
            "key.attributes" : [
              {
                "key.attribute" : "source.decl.attribute.__raw_doc_comment"
              }
            ],
            "key.doc.full_as_xml" : "<Other file=\"Bicycle.swift\" line=\"56\" column=\"22\"><Name>distanceTravelled<\/Name><USR>s:vC7Bicycle7Bicycle17distanceTravelledSd<\/USR><Declaration>private(set) var distanceTravelled: Double<\/Declaration><Abstract><Para>The total distance travelled by the bicycle, in meters.<\/Para><\/Abstract><\/Other>",
            "key.nameoffset" : 1335,
            "key.doc.file" : "Bicycle.swift",
            "key.annotated_decl" : "<Declaration>private(set) var distanceTravelled: <Type usr=\"s:Sd\">Double<\/Type><\/Declaration>",
            "key.doc.name" : "distanceTravelled",
            "key.accessibility" : "source.lang.swift.accessibility.internal",
            "key.setter_accessibility" : "source.lang.swift.accessibility.private",
            "key.parsed_scope.start" : 56,
            "key.filepath" : "Bicycle.swift"
          },
          {
            "key.kind" : "source.lang.swift.decl.function.method.instance",
            "key.offset" : 1754,
            "key.parsed_declaration" : "init(style: Style, gearing: Gearing, handlebar: Handlebar, frameSize centimeters: Int)",
            "key.doc.comment" : "Initializes a new bicycle with the provided parts and specifications.\n\n- parameter style: The style of the bicycle\n- parameter gearing: The gearing of the bicycle\n- parameter handlebar: The handlebar of the bicycle\n- parameter centimeters: The frame size of the bicycle, in centimeters\n\n- returns: A beautiful, brand-new, custom built just for you.",
            "key.namelength" : 86,
            "key.doc.line" : 68,
            "key.bodylength" : 192,
            "key.length" : 86,
            "key.doc.parameters" : [
              {
                "name" : "style",
                "discussion" : [
                  {
                    "Para" : "The style of the bicycle"
                  }
                ]
              },
              {
                "name" : "gearing",
                "discussion" : [
                  {
                    "Para" : "The gearing of the bicycle"
                  }
                ]
              },
              {
                "name" : "handlebar",
                "discussion" : [
                  {
                    "Para" : "The handlebar of the bicycle"
                  }
                ]
              },
              {
                "name" : "centimeters",
                "discussion" : [
                  {
                    "Para" : "The frame size of the bicycle, in centimeters"
                  }
                ]
              }
            ],
            "key.doc.column" : 5,
            "key.parsed_scope.end" : 76,
            "key.usr" : "s:FC7Bicycle7BicyclecFMS0_FT5styleOS0_5Style7gearingOS0_7Gearing9handlebarOS0_9Handlebar9frameSizeSi_S0_",
            "key.doc.file" : "Bicycle.swift",
            "key.nameoffset" : 1754,
            "key.annotated_decl" : "<Declaration>init(style: <Type usr=\"s:OC7Bicycle7Bicycle5Style\">Style<\/Type>, gearing: <Type usr=\"s:OC7Bicycle7Bicycle7Gearing\">Gearing<\/Type>, handlebar: <Type usr=\"s:OC7Bicycle7Bicycle9Handlebar\">Handlebar<\/Type>, frameSize centimeters: <Type usr=\"s:Si\">Int<\/Type>)<\/Declaration>",
            "key.accessibility" : "source.lang.swift.accessibility.internal",
            "key.parsed_scope.start" : 68,
            "key.filepath" : "Bicycle.swift",
            "key.bodyoffset" : 1842,
            "key.doc.declaration" : "init(style: Style, gearing: Gearing, handlebar: Handlebar, frameSize centimeters: Int)",
            "key.name" : "init(style:gearing:handlebar:frameSize:)",
            "key.typename" : "Bicycle.Type -> (style: Bicycle.Style, gearing: Bicycle.Gearing, handlebar: Bicycle.Handlebar, frameSize: Int) -> Bicycle",
            "key.doc.result_discussion" : [
              {
                "Para" : "A beautiful, brand-new, custom built just for you."
              }
            ],
            "key.doc.type" : "Function",
            "key.attributes" : [
              {
                "key.attribute" : "source.decl.attribute.__raw_doc_comment"
              }
            ],
            "key.doc.full_as_xml" : "<Function file=\"Bicycle.swift\" line=\"68\" column=\"5\"><Name>init(style:gearing:handlebar:frameSize:)<\/Name><USR>s:FC7Bicycle7BicyclecFMS0_FT5styleOS0_5Style7gearingOS0_7Gearing9handlebarOS0_9Handlebar9frameSizeSi_S0_<\/USR><Declaration>init(style: Style, gearing: Gearing, handlebar: Handlebar, frameSize centimeters: Int)<\/Declaration><Abstract><Para>Initializes a new bicycle with the provided parts and specifications.<\/Para><\/Abstract><Parameters><Parameter><Name>style<\/Name><Direction isExplicit=\"0\">in<\/Direction><Discussion><Para>The style of the bicycle<\/Para><\/Discussion><\/Parameter><Parameter><Name>gearing<\/Name><Direction isExplicit=\"0\">in<\/Direction><Discussion><Para>The gearing of the bicycle<\/Para><\/Discussion><\/Parameter><Parameter><Name>handlebar<\/Name><Direction isExplicit=\"0\">in<\/Direction><Discussion><Para>The handlebar of the bicycle<\/Para><\/Discussion><\/Parameter><Parameter><Name>centimeters<\/Name><Direction isExplicit=\"0\">in<\/Direction><Discussion><Para>The frame size of the bicycle, in centimeters<\/Para><\/Discussion><\/Parameter><\/Parameters><ResultDiscussion><Para>A beautiful, brand-new, custom built just for you.<\/Para><\/ResultDiscussion><\/Function>",
            "key.doc.name" : "init(style:gearing:handlebar:frameSize:)",
            "key.substructure" : [

            ]
          },
          {
            "key.kind" : "source.lang.swift.decl.function.method.instance",
            "key.offset" : 2152,
            "key.parsed_declaration" : "func travel(distance meters: Double)",
            "key.doc.comment" : "Take a bike out for a spin.\n\n- parameter meters: The distance to travel in meters.",
            "key.namelength" : 31,
            "key.doc.line" : 83,
            "key.bodylength" : 109,
            "key.length" : 31,
            "key.doc.parameters" : [
              {
                "name" : "meters",
                "discussion" : [
                  {
                    "Para" : "The distance to travel in meters."
                  }
                ]
              }
            ],
            "key.doc.column" : 10,
            "key.parsed_scope.end" : 88,
            "key.usr" : "s:FC7Bicycle7Bicycle6travelFS0_FT8distanceSd_T_",
            "key.doc.file" : "Bicycle.swift",
            "key.nameoffset" : 2152,
            "key.annotated_decl" : "<Declaration>func travel(distance meters: <Type usr=\"s:Sd\">Double<\/Type>)<\/Declaration>",
            "key.accessibility" : "source.lang.swift.accessibility.internal",
            "key.parsed_scope.start" : 83,
            "key.filepath" : "Bicycle.swift",
            "key.bodyoffset" : 2185,
            "key.doc.declaration" : "func travel(distance meters: Double)",
            "key.name" : "travel(distance:)",
            "key.typename" : "Bicycle -> (distance: Double) -> ()",
            "key.doc.type" : "Function",
            "key.attributes" : [
              {
                "key.attribute" : "source.decl.attribute.__raw_doc_comment"
              }
            ],
            "key.doc.full_as_xml" : "<Function file=\"Bicycle.swift\" line=\"83\" column=\"10\"><Name>travel(distance:)<\/Name><USR>s:FC7Bicycle7Bicycle6travelFS0_FT8distanceSd_T_<\/USR><Declaration>func travel(distance meters: Double)<\/Declaration><Abstract><Para>Take a bike out for a spin.<\/Para><\/Abstract><Parameters><Parameter><Name>meters<\/Name><Direction isExplicit=\"0\">in<\/Direction><Discussion><Para>The distance to travel in meters.<\/Para><\/Discussion><\/Parameter><\/Parameters><\/Function>",
            "key.doc.name" : "travel(distance:)",
            "key.substructure" : [

            ]
          }
        ]
      }
    ],
    "key.offset" : 0,
    "key.diagnostic_stage" : "source.diagnostic.stage.swift.parse",
    "key.length" : 2298
  }
}
